collab_tunnel/__init__.py
collab_tunnel/crawler.py
collab_tunnel/sitemap.py
collab_tunnel/validator.py
collab_tunnel/vectors.py
collab_tunnel-2.0.0.dist-info/licenses/LICENSE
collab_tunnel-2.0.0.dist-info/METADATA
collab_tunnel-2.0.0.dist-info/WHEEL
collab_tunnel-2.0.0.dist-info/entry_points.txt
collab_tunnel-2.0.0.dist-info/top_level.txt
collab_tunnel-2.0.0.dist-info/RECORD
