Metadata-Version: 2.4
Name: collab-tunnel
Version: 2.0.0
Summary: Python client library for the Collaboration Tunnel Protocol (TCT)
Home-page: https://github.com/antunjurkovic-collab/collab-tunnel-python
Author: Antun Jurkovikj
Author-email: Antun Jurkovikj <antunjurkovic@gmail.com>
License: MIT
Project-URL: Homepage, https://llmpages.org
Project-URL: Documentation, https://llmpages.org/docs/python/
Project-URL: Repository, https://github.com/antunjurkovic-collab/collab-tunnel-python
Project-URL: Bug Tracker, https://github.com/antunjurkovic-collab/collab-tunnel-python/issues
Keywords: ai,crawler,optimization,bandwidth,llm,http,protocol
Classifier: Development Status :: 4 - Beta
Classifier: Intended Audience :: Developers
Classifier: Topic :: Internet :: WWW/HTTP
Classifier: Topic :: Software Development :: Libraries :: Python Modules
Classifier: License :: OSI Approved :: MIT License
Classifier: Programming Language :: Python :: 3
Classifier: Programming Language :: Python :: 3.7
Classifier: Programming Language :: Python :: 3.8
Classifier: Programming Language :: Python :: 3.9
Classifier: Programming Language :: Python :: 3.10
Classifier: Programming Language :: Python :: 3.11
Classifier: Programming Language :: Python :: 3.12
Requires-Python: >=3.7
License-File: LICENSE
Requires-Dist: requests>=2.25.0
Provides-Extra: dev
Requires-Dist: pytest>=6.0; extra == "dev"
Requires-Dist: pytest-cov>=2.0; extra == "dev"
Requires-Dist: black>=21.0; extra == "dev"
Requires-Dist: flake8>=3.9; extra == "dev"
Dynamic: author
Dynamic: home-page
Dynamic: license-file
Dynamic: requires-python
